box_sdk_gen/__init__.py
box_sdk_gen/client.py
box_sdk_gen/box/__init__.py
box_sdk_gen/box/ccg_auth.py
box_sdk_gen/box/developer_token_auth.py
box_sdk_gen/box/errors.py
box_sdk_gen/box/event_stream.py
box_sdk_gen/box/jwt_auth.py
box_sdk_gen/box/oauth.py
box_sdk_gen/box/token_storage.py
box_sdk_gen/internal/__init__.py
box_sdk_gen/internal/base_object.py
box_sdk_gen/internal/errors.py
box_sdk_gen/internal/logging.py
box_sdk_gen/internal/null_value.py
box_sdk_gen/internal/utils.py
box_sdk_gen/managers/__init__.py
box_sdk_gen/managers/ai.py
box_sdk_gen/managers/ai_studio.py
box_sdk_gen/managers/app_item_associations.py
box_sdk_gen/managers/archives.py
box_sdk_gen/managers/authorization.py
box_sdk_gen/managers/avatars.py
box_sdk_gen/managers/chunked_uploads.py
box_sdk_gen/managers/classifications.py
box_sdk_gen/managers/collaboration_allowlist_entries.py
box_sdk_gen/managers/collaboration_allowlist_exempt_targets.py
box_sdk_gen/managers/collections.py
box_sdk_gen/managers/comments.py
box_sdk_gen/managers/device_pinners.py
box_sdk_gen/managers/docgen.py
box_sdk_gen/managers/docgen_template.py
box_sdk_gen/managers/downloads.py
box_sdk_gen/managers/email_aliases.py
box_sdk_gen/managers/events.py
box_sdk_gen/managers/file_classifications.py
box_sdk_gen/managers/file_metadata.py
box_sdk_gen/managers/file_requests.py
box_sdk_gen/managers/file_version_legal_holds.py
box_sdk_gen/managers/file_version_retentions.py
box_sdk_gen/managers/file_versions.py
box_sdk_gen/managers/file_watermarks.py
box_sdk_gen/managers/files.py
box_sdk_gen/managers/folder_classifications.py
box_sdk_gen/managers/folder_locks.py
box_sdk_gen/managers/folder_metadata.py
box_sdk_gen/managers/folder_watermarks.py
box_sdk_gen/managers/folders.py
box_sdk_gen/managers/groups.py
box_sdk_gen/managers/hub_collaborations.py
box_sdk_gen/managers/hub_items.py
box_sdk_gen/managers/hubs.py
box_sdk_gen/managers/integration_mappings.py
box_sdk_gen/managers/invites.py
box_sdk_gen/managers/legal_hold_policies.py
box_sdk_gen-1.17.0.dist-info/licenses/LICENSE
box_sdk_gen-1.17.0.dist-info/METADATA
box_sdk_gen-1.17.0.dist-info/WHEEL
box_sdk_gen-1.17.0.dist-info/top_level.txt
box_sdk_gen-1.17.0.dist-info/RECORD
