Metadata-Version: 2.4
Name: box-sdk-gen
Version: 1.17.0
Summary: Official Box Python Generated SDK
Home-page: https://github.com/box/box-python-sdk-gen.git
Author: Box
Author-email: oss@box.com
License: Apache-2.0, http://www.apache.org/licenses/LICENSE-2.0
Keywords: box,sdk,api,rest,boxsdk,box-sdk-gen
Classifier: Development Status :: 5 - Production/Stable
Classifier: Intended Audience :: Developers
Classifier: License :: OSI Approved :: Apache Software License
Classifier: Programming Language :: Python
Classifier: Programming Language :: Python :: 3.8
Classifier: Programming Language :: Python :: 3.9
Classifier: Programming Language :: Python :: 3.10
Classifier: Programming Language :: Python :: 3.11
Classifier: Programming Language :: Python :: 3.12
Classifier: Programming Language :: Python :: Implementation :: CPython
Classifier: Programming Language :: Python :: Implementation :: PyPy
Classifier: Operating System :: OS Independent
Classifier: Operating System :: POSIX
Classifier: Operating System :: Microsoft :: Windows
Classifier: Operating System :: MacOS :: MacOS X
Classifier: Topic :: Software Development :: Libraries :: Python Modules
License-File: LICENSE
Requires-Dist: requests
Requires-Dist: requests-toolbelt
Provides-Extra: test
Requires-Dist: pytest; extra == "test"
Requires-Dist: pytest-timeout; extra == "test"
Requires-Dist: pytest-cov; extra == "test"
Requires-Dist: pytest-rerunfailures; extra == "test"
Requires-Dist: pyjwt>=1.7.0; extra == "test"
Requires-Dist: cryptography>=3; extra == "test"
Provides-Extra: dev
Requires-Dist: tox; extra == "dev"
Provides-Extra: jwt
Requires-Dist: pyjwt>=1.7.0; extra == "jwt"
Requires-Dist: cryptography>=3; extra == "jwt"
Dynamic: author
Dynamic: author-email
Dynamic: classifier
Dynamic: description
Dynamic: description-content-type
Dynamic: home-page
Dynamic: keywords
Dynamic: license
Dynamic: license-file
Dynamic: provides-extra
Dynamic: requires-dist
Dynamic: summary
